async4trail/__init__.py
async4trail/async4trail.py
async4trail/async4trail2.py
async4trail-1.9.dist-info/METADATA
async4trail-1.9.dist-info/WHEEL
async4trail-1.9.dist-info/entry_points.txt
async4trail-1.9.dist-info/top_level.txt
async4trail-1.9.dist-info/RECORD
